django_shapeshifter-18.9.23.dist-info/LICENSE.txt
django_shapeshifter-18.9.23.dist-info/METADATA
django_shapeshifter-18.9.23.dist-info/RECORD
django_shapeshifter-18.9.23.dist-info/WHEEL
django_shapeshifter-18.9.23.dist-info/top_level.txt
shapeshifter/__init__.py
shapeshifter/mixins.py
shapeshifter/views.py
shapeshifter/tests/__init__.py
shapeshifter/tests/conftest.py
shapeshifter/tests/test_multi_form_view.py
shapeshifter/tests/test_multi_model_form_view.py
shapeshifter/tests/testapp/__init__.py
shapeshifter/tests/testapp/forms.py
shapeshifter/tests/testapp/urls.py
shapeshifter/tests/testapp/views.py
shapeshifter/tests/testapp/templates/testapp/forms.html
