Metadata-Version: 1.1
Name: django-shapeshifter
Version: 18.9.23
Summary: Class-based views for simultaneously handling multiple forms in Django
Home-page: https://github.com/kennethlove/django-shapeshifter
Author: Kenneth Love
Author-email: kennethlove@gmail.com
License: Apache 2.0
Keywords: forms,django,multi,cbv,class-based views
Platform: UNKNOWN
Classifier: Development Status :: 4 - Beta
Classifier: Environment :: Web Environment
Classifier: Framework :: Django
Classifier: Intended Audience :: Developers
Classifier: License :: OSI Approved :: Apache Software License
Classifier: Natural Language :: English
Classifier: Programming Language :: Python :: 3 :: Only
Classifier: Topic :: Software Development :: User Interfaces
